CHANGELOG
LICENSE
MANIFEST.in
README.rst
setup.py
fluidity/__init__.py
fluidity/backwardscompat.py
fluidity/machine.py
fluidity_sm.egg-info/PKG-INFO
fluidity_sm.egg-info/SOURCES.txt
fluidity_sm.egg-info/dependency_links.txt
fluidity_sm.egg-info/top_level.txt