Metadata-Version: 1.0
Name: fluidity-sm
Version: 0.2.0
Summary: Fluidity: state machine implementation for Python objects
Home-page: https://github.com/nsi-iff/fluidity
Author: Rodrigo Manhães
Author-email: rmanhaes@gmail.com
License: MIT License
Keywords: state machine python dsl
Platform: UNKNOWN
Classifier: Development Status :: 4 - Beta
Classifier: Intended Audience :: Developers
Classifier: License :: OSI Approved :: MIT License
Classifier: Programming Language :: Python
Classifier: Programming Language :: Python :: 2.4
Classifier: Programming Language :: Python :: 2.5
Classifier: Programming Language :: Python :: 2.6
Classifier: Programming Language :: Python :: 2.7
Classifier: Programming Language :: Python :: 3.1
Classifier: Programming Language :: Python :: 3.2
Classifier: Topic :: Software Development :: Libraries
